taxontools/__init__.py
taxontools/cli.py
taxontools/pipelines.py
taxontools/versions.py
taxontools/one_kp/1kp.acc.taxon.txt
taxontools/one_kp/estimated_species_tree.tree
taxontools/src/1kp.py
taxontools/src/__init__.py
taxontools/src/blast_assign.py
taxontools/src/taxon.py
taxontools-0.3.2.dist-info/LICENSE
taxontools-0.3.2.dist-info/METADATA
taxontools-0.3.2.dist-info/WHEEL
taxontools-0.3.2.dist-info/entry_points.txt
taxontools-0.3.2.dist-info/top_level.txt
taxontools-0.3.2.dist-info/RECORD
