Metadata-Version: 2.1
Name: taxontools
Version: 0.3.2
Summary: A toolkit for analyzing Taxonomy
Home-page: https://github.com/SouthernCD/taxontools
Author: Yuxing Xu
Author-email: xuyuxing@mail.kib.ac.cn
Requires-Python: >=3.5
License-File: LICENSE
Requires-Dist: yxtree
Requires-Dist: yxutil
Requires-Dist: yxmath
Requires-Dist: mlxtend >=0.17.2
Requires-Dist: scipy >=1.4.1
Requires-Dist: numpy >=1.18.1
Requires-Dist: biopython <=1.80
